{
  "annotations": {
    "list": [
      {
        "builtIn": 1,
        "datasource": {
          "type": "grafana",
          "uid": "-- Grafana --"
        },
        "enable": true,
        "hide": true,
        "iconColor": "rgba(0, 211, 255, 1)",
        "name": "Annotations & Alerts",
        "type": "dashboard"
      }
    ]
  },
  "editable": true,
  "fiscalYearStartMonth": 0,
  "graphTooltip": 0,
  "links": [],
  "panels": [
    {
      "datasource": {
        "type": "prometheus",
        "uid": "open5gsmetrics"
      },
      "gridPos": {
        "h": 8,
        "w": 12,
        "x": 0,
        "y": 0
      },
      "id": 4,
      "options": {
        "alertInstanceLabelFilter": "",
        "alertName": "",
        "dashboardAlerts": false,
        "groupBy": [],
        "groupMode": "default",
        "maxItems": 20,
        "sortOrder": 1,
        "stateFilter": {
          "error": true,
          "firing": true,
          "noData": false,
          "normal": false,
          "pending": true
        },
        "viewMode": "list"
      },
      "pluginVersion": "10.4.0",
      "targets": [
        {
          "datasource": {
            "type": "prometheus",
            "uid": "open5gsmetrics"
          },
          "disableTextWrap": false,
          "editorMode": "builder",
          "expr": "ALERTS_FOR_STATE",
          "fullMetaSearch": false,
          "includeNullMetadata": true,
          "instant": false,
          "legendFormat": "__auto",
          "range": true,
          "refId": "A",
          "useBackend": false
        }
      ],
      "title": "Panel Title",
      "type": "alertlist"
    },
    {
      "datasource": {
        "type": "prometheus",
        "uid": "open5gsmetrics"
      },
      "fieldConfig": {
        "defaults": {
          "color": {
            "mode": "palette-classic"
          },
          "custom": {
            "axisBorderShow": false,
            "axisCenteredZero": false,
            "axisColorMode": "text",
            "axisLabel": "",
            "axisPlacement": "auto",
            "barAlignment": 0,
            "drawStyle": "line",
            "fillOpacity": 0,
            "gradientMode": "none",
            "hideFrom": {
              "legend": false,
              "tooltip": false,
              "viz": false
            },
            "insertNulls": false,
            "lineInterpolation": "linear",
            "lineWidth": 1,
            "pointSize": 5,
            "scaleDistribution": {
              "type": "linear"
            },
            "showPoints": "auto",
            "spanNulls": false,
            "stacking": {
              "group": "A",
              "mode": "none"
            },
            "thresholdsStyle": {
              "mode": "off"
            }
          },
          "mappings": [],
          "thresholds": {
            "mode": "absolute",
            "steps": [
              {
                "color": "green",
                "value": null
              },
              {
                "color": "red",
                "value": 80
              }
            ]
          }
        },
        "overrides": []
      },
      "gridPos": {
        "h": 8,
        "w": 12,
        "x": 12,
        "y": 0
      },
      "id": 1,
      "options": {
        "legend": {
          "calcs": [],
          "displayMode": "list",
          "placement": "bottom",
          "showLegend": true
        },
        "tooltip": {
          "mode": "single",
          "sort": "none"
        }
      },
      "targets": [
        {
          "datasource": {
            "type": "prometheus",
            "uid": "open5gsmetrics"
          },
          "editorMode": "code",
          "expr": "fivegs_upffunction_upf_qosflows{job=\"upf1\"}",
          "instant": false,
          "legendFormat": "UPF number of QoS flows",
          "range": true,
          "refId": "UPF number of QoS flows"
        },
        {
          "datasource": {
            "type": "prometheus",
            "uid": "open5gsmetrics"
          },
          "editorMode": "code",
          "expr": "fivegs_upffunction_upf_qosflows{job=\"upf1\",dnn=\"$dnn\"}",
          "instant": false,
          "legendFormat": "UPF number of QoS flows for DNN {{dnn}}",
          "range": true,
          "refId": "UPF number of QoS flows for DNN"
        }
      ],
      "title": "UPF number of QoS flows (upf1)",
      "type": "timeseries"
    },
    {
      "datasource": {
        "type": "prometheus",
        "uid": "open5gsmetrics"
      },
      "fieldConfig": {
        "defaults": {
          "color": {
            "mode": "palette-classic"
          },
          "custom": {
            "axisBorderShow": false,
            "axisCenteredZero": false,
            "axisColorMode": "text",
            "axisLabel": "",
            "axisPlacement": "auto",
            "barAlignment": 0,
            "drawStyle": "line",
            "fillOpacity": 0,
            "gradientMode": "none",
            "hideFrom": {
              "legend": false,
              "tooltip": false,
              "viz": false
            },
            "insertNulls": false,
            "lineInterpolation": "linear",
            "lineWidth": 1,
            "pointSize": 5,
            "scaleDistribution": {
              "type": "linear"
            },
            "showPoints": "auto",
            "spanNulls": false,
            "stacking": {
              "group": "A",
              "mode": "none"
            },
            "thresholdsStyle": {
              "mode": "off"
            }
          },
          "mappings": [],
          "thresholds": {
            "mode": "absolute",
            "steps": [
              {
                "color": "green",
                "value": null
              },
              {
                "color": "red",
                "value": 80
              }
            ]
          }
        },
        "overrides": []
      },
      "gridPos": {
        "h": 8,
        "w": 12,
        "x": 0,
        "y": 8
      },
      "id": 2,
      "options": {
        "legend": {
          "calcs": [],
          "displayMode": "list",
          "placement": "bottom",
          "showLegend": true
        },
        "tooltip": {
          "mode": "single",
          "sort": "none"
        }
      },
      "targets": [
        {
          "datasource": {
            "type": "prometheus",
            "uid": "open5gsmetrics"
          },
          "editorMode": "code",
          "expr": "fivegs_upffunction_upf_qosflows{job=\"upf2\"}",
          "instant": false,
          "legendFormat": "UPF number of QoS flows",
          "range": true,
          "refId": "UPF number of QoS flows"
        },
        {
          "datasource": {
            "type": "prometheus",
            "uid": "open5gsmetrics"
          },
          "editorMode": "code",
          "expr": "fivegs_upffunction_upf_qosflows{job=\"upf2\",dnn=\"$dnn\"}",
          "instant": false,
          "legendFormat": "UPF number of QoS flows for DNN {{dnn}}",
          "range": true,
          "refId": "UPF number of QoS flows for DNN"
        }
      ],
      "title": "UPF number of QoS flows (upf2)",
      "type": "timeseries"
    },
    {
      "datasource": {
        "type": "prometheus",
        "uid": "open5gsmetrics"
      },
      "fieldConfig": {
        "defaults": {
          "color": {
            "mode": "palette-classic"
          },
          "custom": {
            "axisBorderShow": false,
            "axisCenteredZero": false,
            "axisColorMode": "text",
            "axisLabel": "",
            "axisPlacement": "auto",
            "barAlignment": 0,
            "drawStyle": "line",
            "fillOpacity": 0,
            "gradientMode": "none",
            "hideFrom": {
              "legend": false,
              "tooltip": false,
              "viz": false
            },
            "insertNulls": false,
            "lineInterpolation": "linear",
            "lineWidth": 1,
            "pointSize": 5,
            "scaleDistribution": {
              "type": "linear"
            },
            "showPoints": "auto",
            "spanNulls": false,
            "stacking": {
              "group": "A",
              "mode": "none"
            },
            "thresholdsStyle": {
              "mode": "off"
            }
          },
          "mappings": [],
          "thresholds": {
            "mode": "absolute",
            "steps": [
              {
                "color": "green",
                "value": null
              },
              {
                "color": "red",
                "value": 80
              }
            ]
          }
        },
        "overrides": []
      },
      "gridPos": {
        "h": 8,
        "w": 12,
        "x": 12,
        "y": 8
      },
      "id": 3,
      "options": {
        "legend": {
          "calcs": [],
          "displayMode": "list",
          "placement": "bottom",
          "showLegend": true
        },
        "tooltip": {
          "mode": "single",
          "sort": "none"
        }
      },
      "targets": [
        {
          "datasource": {
            "type": "prometheus",
            "uid": "open5gsmetrics"
          },
          "editorMode": "code",
          "expr": "fivegs_upffunction_upf_qosflows{job=\"upf3\"}",
          "instant": false,
          "legendFormat": "UPF number of QoS flows",
          "range": true,
          "refId": "UPF number of QoS flows"
        },
        {
          "datasource": {
            "type": "prometheus",
            "uid": "open5gsmetrics"
          },
          "editorMode": "code",
          "expr": "fivegs_upffunction_upf_qosflows{job=\"upf3\",dnn=\"$dnn\"}",
          "instant": false,
          "legendFormat": "UPF number of QoS flows for DNN {{dnn}}",
          "range": true,
          "refId": "UPF number of QoS flows for DNN"
        }
      ],
      "title": "UPF number of QoS flows (upf3)",
      "type": "timeseries"
    },
    {
      "datasource": {
        "type": "prometheus",
        "uid": "open5gsmetrics"
      },
      "fieldConfig": {
        "defaults": {
          "color": {
            "mode": "palette-classic"
          },
          "custom": {
            "axisBorderShow": false,
            "axisCenteredZero": false,
            "axisColorMode": "text",
            "axisLabel": "",
            "axisPlacement": "auto",
            "barAlignment": 0,
            "drawStyle": "line",
            "fillOpacity": 0,
            "gradientMode": "none",
            "hideFrom": {
              "legend": false,
              "tooltip": false,
              "viz": false
            },
            "insertNulls": false,
            "lineInterpolation": "linear",
            "lineWidth": 1,
            "pointSize": 5,
            "scaleDistribution": {
              "type": "linear"
            },
            "showPoints": "auto",
            "spanNulls": false,
            "stacking": {
              "group": "A",
              "mode": "none"
            },
            "thresholdsStyle": {
              "mode": "off"
            }
          },
          "mappings": [],
          "thresholds": {
            "mode": "absolute",
            "steps": [
              {
                "color": "green",
                "value": null
              },
              {
                "color": "red",
                "value": 80
              }
            ]
          }
        },
        "overrides": []
      },
      "gridPos": {
        "h": 8,
        "w": 12,
        "x": 0,
        "y": 16
      },
      "id": 5,
      "options": {
        "legend": {
          "calcs": [],
          "displayMode": "list",
          "placement": "bottom",
          "showLegend": true
        },
        "tooltip": {
          "mode": "single",
          "sort": "none"
        }
      },
      "targets": [
        {
          "datasource": {
            "type": "prometheus",
            "uid": "open5gsmetrics"
          },
          "editorMode": "code",
          "expr": "fivegs_upffunction_upf_qosflows{job=\"upf4\"}",
          "instant": false,
          "legendFormat": "UPF number of QoS flows",
          "range": true,
          "refId": "UPF number of QoS flows"
        },
        {
          "datasource": {
            "type": "prometheus",
            "uid": "open5gsmetrics"
          },
          "editorMode": "code",
          "expr": "fivegs_upffunction_upf_qosflows{job=\"upf4\",dnn=\"$dnn\"}",
          "instant": false,
          "legendFormat": "UPF number of QoS flows for DNN {{dnn}}",
          "range": true,
          "refId": "UPF number of QoS flows for DNN"
        }
      ],
      "title": "UPF number of QoS flows (upf4)",
      "type": "timeseries"
    },
    {
      "datasource": {
        "type": "prometheus",
        "uid": "open5gsmetrics"
      },
      "fieldConfig": {
        "defaults": {
          "color": {
            "mode": "palette-classic"
          },
          "custom": {
            "axisBorderShow": false,
            "axisCenteredZero": false,
            "axisColorMode": "text",
            "axisLabel": "",
            "axisPlacement": "auto",
            "barAlignment": 0,
            "drawStyle": "line",
            "fillOpacity": 0,
            "gradientMode": "none",
            "hideFrom": {
              "legend": false,
              "tooltip": false,
              "viz": false
            },
            "insertNulls": false,
            "lineInterpolation": "linear",
            "lineWidth": 1,
            "pointSize": 5,
            "scaleDistribution": {
              "type": "linear"
            },
            "showPoints": "auto",
            "spanNulls": false,
            "stacking": {
              "group": "A",
              "mode": "none"
            },
            "thresholdsStyle": {
              "mode": "off"
            }
          },
          "mappings": [],
          "thresholds": {
            "mode": "absolute",
            "steps": [
              {
                "color": "green",
                "value": null
              },
              {
                "color": "red",
                "value": 80
              }
            ]
          }
        },
        "overrides": []
      },
      "gridPos": {
        "h": 8,
        "w": 12,
        "x": 12,
        "y": 16
      },
      "id": 6,
      "options": {
        "legend": {
          "calcs": [],
          "displayMode": "list",
          "placement": "bottom",
          "showLegend": true
        },
        "tooltip": {
          "mode": "single",
          "sort": "none"
        }
      },
      "targets": [
        {
          "datasource": {
            "type": "prometheus",
            "uid": "open5gsmetrics"
          },
          "editorMode": "code",
          "expr": "fivegs_upffunction_upf_qosflows{job=\"upf5\"}",
          "instant": false,
          "legendFormat": "UPF number of QoS flows",
          "range": true,
          "refId": "UPF number of QoS flows"
        },
        {
          "datasource": {
            "type": "prometheus",
            "uid": "open5gsmetrics"
          },
          "editorMode": "code",
          "expr": "fivegs_upffunction_upf_qosflows{job=\"upf5\",dnn=\"$dnn\"}",
          "instant": false,
          "legendFormat": "UPF number of QoS flows for DNN {{dnn}}",
          "range": true,
          "refId": "UPF number of QoS flows for DNN"
        }
      ],
      "title": "UPF number of QoS flows (upf5)",
      "type": "timeseries"
    }
  ],
  "schemaVersion": 39,
  "tags": [],
  "templating": {
    "list": [
      {
        "current": {
          "selected": false,
          "text": "internet",
          "value": "internet"
        },
        "datasource": {
          "type": "prometheus",
          "uid": "open5gsmetrics"
        },
        "definition": "label_values(dnn)",
        "hide": 0,
        "includeAll": false,
        "label": "DNN",
        "multi": false,
        "name": "dnn",
        "options": [],
        "query": {
          "qryType": 1,
          "query": "label_values(dnn)",
          "refId": "open5gsmetrics-dnn"
        },
        "refresh": 1,
        "regex": "",
        "skipUrlSync": false,
        "sort": 0,
        "type": "query"
      }
    ]
  },
  "time": {
    "from": "now-6h",
    "to": "now"
  },
  "timepicker": {},
  "timezone": "browser",
  "title": "UPF dashboard",
  "uid": "upfdashboard",
  "version": 1,
  "weekStart": ""
}